memoized.py
dimagi_memoized-1.1.3.dist-info/DESCRIPTION.rst
dimagi_memoized-1.1.3.dist-info/METADATA
dimagi_memoized-1.1.3.dist-info/RECORD
dimagi_memoized-1.1.3.dist-info/WHEEL
dimagi_memoized-1.1.3.dist-info/metadata.json
dimagi_memoized-1.1.3.dist-info/top_level.txt
