Metadata-Version: 2.0
Name: dimagi-memoized
Version: 1.1.3
Summary: A simple memoization decorator that's also memory efficient on instance methods
Home-page: https://github.com/dimagi/memoized
Author: Dimagi
Author-email: dev@dimagi.com
License: BSD-3
Platform: UNKNOWN
Provides-Extra: test
Provides-Extra: test
Requires-Dist: nose; extra == 'test'
Requires-Dist: testil; extra == 'test'
